LICENSE.txt
README.md
VERSION.txt
pyproject.toml
setup.cfg
setup.py
smarterai/__init__.py
smarterai/smarterApi.py
smarterai/smarterInterface.py
smarterai/smarterStore.py
smarterai.egg-info/PKG-INFO
smarterai.egg-info/SOURCES.txt
smarterai.egg-info/dependency_links.txt
smarterai.egg-info/top_level.txt