Metadata-Version: 2.1
Name: smarterai
Version: 1.3.1
Summary: smarter.ai Python API
Home-page: https://www.smarter.ai/
Author: Nevine Soliman and Carlos Medina
Author-email: dev@smarter.ai
License: UNKNOWN
Keywords: machine learning,artificial intelligence
Platform: UNKNOWN
Classifier: Programming Language :: Python :: 3
Classifier: License :: OSI Approved :: MIT License
Classifier: Operating System :: OS Independent
Requires-Python: >=3
